plutopy/__init__.py
plutopy/excel.py
plutopy-0.0.1.dist-info/LICENSE
plutopy-0.0.1.dist-info/METADATA
plutopy-0.0.1.dist-info/WHEEL
plutopy-0.0.1.dist-info/top_level.txt
plutopy-0.0.1.dist-info/RECORD
