Metadata-Version: 2.1
Name: plutopy
Version: 0.0.1
Summary: WardenAllen's Library Package
Home-page: https://gitee.com/WardenAllen
Author: WardenAllen
Author-email: 908824040@qq.com
License: UNKNOWN
Platform: UNKNOWN
Classifier: Programming Language :: Python :: 3
Classifier: License :: OSI Approved :: MIT License
Classifier: Operating System :: OS Independent
Requires-Python: >=3.6
Requires-Dist: xlrd
Requires-Dist: toml
